agent/__init__.py
agent/agent_ai.py
agent/agent_services.py
agent/config.py
agent/utilities.py
agtest-0.2.3.dist-info/licenses/LICENSE
agtest-0.2.3.dist-info/METADATA
agtest-0.2.3.dist-info/WHEEL
agtest-0.2.3.dist-info/entry_points.txt
agtest-0.2.3.dist-info/top_level.txt
agtest-0.2.3.dist-info/RECORD
