Metadata-Version: 2.4
Name: agtest
Version: 0.2.3
Summary: AI-powered tool to automatically generate compliant unit tests for FastAPI controllers and service layers, enforcing strict project standards.
Author: Ankit Negi
Author-email: ankit.negi@47billion.com
License: MIT
Classifier: Programming Language :: Python :: 3
Classifier: License :: OSI Approved :: MIT License
Requires-Python: >=3.10
License-File: LICENSE
Requires-Dist: google-generativeai>=0.8.5
Requires-Dist: openai>=1.55.1
Requires-Dist: anthropic>=0.34.1
Dynamic: license-file
Dynamic: requires-dist
